robotAzureSync/__init__.py
robotAzureSync/robotAzureSync.py
robotAzureSync/robotAzureSyncGet.py
robotAzureSync/robotAzureSyncPatch.py
robotAzureSync/syncUtils.py
robotAzureSync/tests/__init__.py
robotAzureSync/tests/test_robot_azure_sync_get.py
robotAzureSync-1.0.0.dist-info/METADATA
robotAzureSync-1.0.0.dist-info/WHEEL
robotAzureSync-1.0.0.dist-info/entry_points.txt
robotAzureSync-1.0.0.dist-info/top_level.txt
robotAzureSync-1.0.0.dist-info/RECORD
